wavestate/bunch/__init__.py
wavestate/bunch/_version.py
wavestate/bunch/bunch.py
wavestate/bunch/deep_bunch.py
wavestate/bunch/depbunch.py
wavestate/bunch/hdf_deep_bunch.py
wavestate/bunch/interrupt_delay.py
wavestate/bunch/quickbunch.py
wavestate/bunch/shadow_bunch.py
wavestate/bunch/tag_bunch.py
wavestate.bunch-0.9.1.dist-info/METADATA
wavestate.bunch-0.9.1.dist-info/NOTICE
wavestate.bunch-0.9.1.dist-info/WHEEL
wavestate.bunch-0.9.1.dist-info/top_level.txt
wavestate.bunch-0.9.1.dist-info/RECORD
