Metadata-Version: 2.1
Name: wavestate.bunch
Version: 0.9.1
Summary: bunch container objects like Matlab structs
Home-page: https://github.com/wavestate/wavestate-bunch
Author: Lee McCuller
Author-email: mcculler@mit.edu
License: Apache-2.0
Project-URL: Bug Tracker, https://github.com/wavestate/wavestate-bunch/issues
Project-URL: Source Code, https://github.com/wavestate/wavestate-bunch
Platform: UNKNOWN
Classifier: Intended Audience :: Science/Research
Classifier: License :: OSI Approved :: Apache Software License
Classifier: Operating System :: OS Independent
Classifier: Programming Language :: Python
Classifier: Programming Language :: Python :: 3
Classifier: Topic :: Scientific/Engineering :: Physics
License-File: LICENSES/Apache-2.0.txt
License-File: LICENSES/CC0-1.0.txt
License-File: NOTICE
